ayn_utils-0.1.0.dist-info/licenses/LICENSE.txt
pdf/__init__.py
pdf/main.py
pdf/cli/__init__.py
pdf/cli/commands.py
pdf/core/__init__.py
pdf/core/exceptions.py
pdf/core/pdf_manager.py
pdf/operations/__init__.py
pdf/operations/merge.py
pdf/operations/rotate.py
pdf/operations/split.py
ayn_utils-0.1.0.dist-info/METADATA
ayn_utils-0.1.0.dist-info/WHEEL
ayn_utils-0.1.0.dist-info/entry_points.txt
ayn_utils-0.1.0.dist-info/top_level.txt
ayn_utils-0.1.0.dist-info/RECORD
